[
{
  "model": "courses.subject",
  "pk": 1,
  "fields": {
    "title": "Music",
    "slug": "music"
  }
},
{
  "model": "courses.subject",
  "pk": 2,
  "fields": {
    "title": "Arts",
    "slug": "arts"
  }
},
{
  "model": "courses.subject",
  "pk": 3,
  "fields": {
    "title": "Politics",
    "slug": "politics"
  }
},
{
  "model": "courses.subject",
  "pk": 4,
  "fields": {
    "title": "History",
    "slug": "history"
  }
},
{
  "model": "courses.subject",
  "pk": 5,
  "fields": {
    "title": "Health and Social",
    "slug": "health-and-social"
  }
},
{
  "model": "courses.subject",
  "pk": 6,
  "fields": {
    "title": "Math",
    "slug": "math"
  }
},
{
  "model": "courses.subject",
  "pk": 7,
  "fields": {
    "title": "Literature",
    "slug": "literature"
  }
},
{
  "model": "courses.subject",
  "pk": 8,
  "fields": {
    "title": "Physics",
    "slug": "physics"
  }
}
]
